auth_api/__init__.py
auth_api/config.py
auth_api/main.py
auth_api/oauth2_client.py
atk_auth_api-0.3.0.dist-info/METADATA
atk_auth_api-0.3.0.dist-info/WHEEL
atk_auth_api-0.3.0.dist-info/RECORD
