Metadata-Version: 2.1
Name: atk-auth-api
Version: 0.3.0
Summary: An API for interfacing with DEX IdP
Author: Panu Oksiala
Author-email: panu@oksiala.fi
Requires-Python: >=3.10,<4.0
Classifier: Programming Language :: Python :: 3
Classifier: Programming Language :: Python :: 3.10
Classifier: Programming Language :: Python :: 3.11
Requires-Dist: fastapi (>=0.101.0,<0.102.0)
Requires-Dist: pydantic (>=2.1.1,<3.0.0)
Requires-Dist: pyjwt[crypto] (>=2.8.0,<3.0.0)
Requires-Dist: pyyaml (>=6.0.1,<7.0.0)
Requires-Dist: requests (>=2.31.0,<3.0.0)
Requires-Dist: requests-oauthlib (>=1.3.1,<2.0.0)
Requires-Dist: sentry-sdk[fastapi] (>=1.29.2,<2.0.0)
